{
  "type": "tanium-signal",
  "typeVersion": "1.0",
  "isSchemaValid": true,
  "createdAt": "2026-04-13T15:14:13.943Z",
  "updatedAt": "2026-04-13T15:14:13.943Z",
  "data": {
    "id": "TR-EXEC-002: CLR Hosting in Native Process (.NET In-Memory Execution)",
    "name": "TR-EXEC-002: CLR Hosting in Native Process (.NET In-Memory Execution)",
    "description": "Detects mscoree.dll loaded by a native (non-.NET) process, or imports of CLRCreateInstance / _CorDllMain. This is the primary mechanism for execute-assembly, Cobalt Strike BOF .NET execution, and SharpPick-style attacks. _CorDllMain: Score=100, MalCount=15. CLRCreateInstance: Score=100.",
    "contents": "(process.modules contains 'mscoree.dll' OR process.modules contains 'clrjit.dll') AND process.name != 'powershell.exe' AND process.name != 'pwsh.exe' AND process.name != 'msbuild.exe' AND process.name != 'csc.exe' AND process.name != 'vbc.exe' AND process.name != 'devenv.exe' AND process.name != 'dotnet.exe' AND process.name != 'w3wp.exe' AND process.name != 'iisexpress.exe'",
    "syntax_version": 1,
    "mitreAttack": {
      "techniques": [
        {
          "id": "T1620",
          "name": "Reflective Code Loading"
        }
      ]
    },
    "platforms": [
      "windows"
    ],
    "labels": [
      "Windows",
      "Defense Evasion"
    ]
  }
}
