[
    {
        "Item_Name":  "Suspicious Curl.EXE Download",
        "Type":  "Sigma Rule",
        "Baseline_Rarity_Score":  100,
        "Malicious_Count":  1,
        "Last_Seen":  "2025-09-22"
    },
    {
        "Item_Name":  "Launch Agent/Daemon Execution Via Launchctl",
        "Type":  "Sigma Rule",
        "Baseline_Rarity_Score":  100,
        "Malicious_Count":  1,
        "Last_Seen":  "2025-09-22"
    },
    {
        "Item_Name":  "Curl Usage on Linux",
        "Type":  "Sigma Rule",
        "Baseline_Rarity_Score":  100,
        "Malicious_Count":  1,
        "Last_Seen":  "2025-09-22"
    },
    {
        "Item_Name":  "Usage Of Web Request Commands And Cmdlets",
        "Type":  "Sigma Rule",
        "Baseline_Rarity_Score":  100,
        "Malicious_Count":  2,
        "Last_Seen":  "2025-09-22"
    },
    {
        "Item_Name":  "Potentially Suspicious Execution From Tmp Folder",
        "Type":  "Sigma Rule",
        "Baseline_Rarity_Score":  100,
        "Malicious_Count":  1,
        "Last_Seen":  "2025-02-10"
    },
    {
        "Item_Name":  "System Information Discovery Via Sysctl - MacOS",
        "Type":  "Sigma Rule",
        "Baseline_Rarity_Score":  100,
        "Malicious_Count":  1,
        "Last_Seen":  "2025-02-06"
    },
    {
        "Item_Name":  "System Information Discovery Using sw_vers",
        "Type":  "Sigma Rule",
        "Baseline_Rarity_Score":  100,
        "Malicious_Count":  1,
        "Last_Seen":  "2025-02-06"
    }
]
