[
    {
        "Item_Name":  "IVIEWERS LIBRARY (Unverified)",
        "Type":  "Certificate",
        "Baseline_Rarity_Score":  100,
        "Malicious_Count":  3,
        "Last_Seen":  "2024-02-03"
    },
    {
        "Item_Name":  "JSl_mai (Unverified)",
        "Type":  "Certificate",
        "Baseline_Rarity_Score":  100,
        "Malicious_Count":  2,
        "Last_Seen":  "2024-02-03"
    },
    {
        "Item_Name":  "VIEWTEST (Unverified)",
        "Type":  "Certificate",
        "Baseline_Rarity_Score":  100,
        "Malicious_Count":  1,
        "Last_Seen":  "2025-09-04"
    },
    {
        "Item_Name":  "Adobe Inc.; DigiCert EV Code Signing CA (SHA2); DigiCert (Verified)",
        "Type":  "Certificate",
        "Baseline_Rarity_Score":  100,
        "Malicious_Count":  1,
        "Last_Seen":  "2024-04-01"
    },
    {
        "Item_Name":  "log.dll (Unverified)",
        "Type":  "Certificate",
        "Baseline_Rarity_Score":  100,
        "Malicious_Count":  8,
        "Last_Seen":  "2024-02-03"
    },
    {
        "Item_Name":  "AdFind (Unverified)",
        "Type":  "Certificate",
        "Baseline_Rarity_Score":  100,
        "Malicious_Count":  3,
        "Last_Seen":  "2025-03-08"
    },
    {
        "Item_Name":  "TODO: \u003cProduct name\u003e (Unverified)",
        "Type":  "Certificate",
        "Baseline_Rarity_Score":  100,
        "Malicious_Count":  10,
        "Last_Seen":  "2025-01-11"
    },
    {
        "Item_Name":  "Unsigned (Unverified)",
        "Type":  "Certificate",
        "Baseline_Rarity_Score":  100,
        "Malicious_Count":  4,
        "Last_Seen":  "2025-09-14"
    }
]
